{"version":"6.1","id":"TYPEBOT_ID_AQUI","name":"Meutype","events":[{"id":"fz652x59ej45iy6tzcur72vt","outgoingEdgeId":"cxzi8bih4jb9secnam8gjryo","graphCoordinates":{"x":-202.39,"y":-314.77},"type":"start"}],"groups":[{"id":"xfz111nmk722d2gjtpdo7s04","title":"Saudação","graphCoordinates":{"x":-220.93,"y":-233.84},"blocks":[{"id":"gbcsyrcgpsdolmkr5jf6ujhf","type":"Webhook","options":{"isCustomBody":true,"isExecutedOnClient":false,"webhook":{"headers":[{"id":"xzy2oegi5xwawia94p82m8nm","key":"Content-Type","value":"application/json"}],"url":"https://n8n.srv1391217.hstgr.cloud/webhook/typebot-webhook","body":"{\n  \"telefone\": \"{{telefone}}\",\n  \"nome\": \"{{pushName}}\",\n  \"jid\": \"{{remoteJid}}\",\n  \"data\": \"{{data}}\",\n  \"hora\": \"{{hora}}\",\n  \"id\": \"{{id}}\",\n  \"instancia\": \"{{instanceName}}\",\n  \"sessionId\": \"sessionId\"\n}"}}},{"id":"woauvuhmf4mmhbi740dv32rx","type":"text","content":{"richText":[{"id":"9oL10V-A8y","type":"p","children":[{"bold":true,"text":"Olá! {{pushName}}, Tudo bem? 😊"},{"text":"\nPara prepararmos o orçamento ideal para você, poderia nos informar qual estrutura está procurando hoje?"}]}]}},{"id":"h31zpi1h9nmis0pa8ta16tgf","type":"image","content":{"url":"https://exemplo.com/sua-imagem.png","clickLink":{"alt":"oxi"}}},{"id":"uk03jlccf9x3gqyfchqjjyao","type":"text","content":{"richText":[{"id":"6OAswJT5vC","type":"p","children":[{"bold":true,"text":"Para começar, escolha uma das opções abaixo:"}]},{"id":"vKuosJP4M-","type":"p","children":[{"text":""}]},{"id":"vdj51s509E","type":"p","children":[{"text":"1️⃣ "},{"bold":true,"text":"Mini Porta-Paletes"},{"text":"\n2️⃣ "},{"bold":true,"text":"Porta-Paletes"}]},{"id":"QdpVOqVzK7","type":"p","children":[{"text":""}]},{"id":"X4V4spDceJ","type":"p","children":[{"text":"👉 "},{"text":"Digite apenas o número da opção desejada.","italic":true}]}]}},{"id":"v0nhk4gdykkic8lstzakzlhh","type":"number input","options":{"variableId":"vpppmv6tfnun3soi0kqd35677","labels":{"placeholder":"Digite uma opção","button":"Enviar"},"locale":"pt-PT"}},{"id":"t5si14u2942hdocl91ikyzys","type":"Condition","items":[{"id":"zhr29u0ailqn8hzxqascn2tk","outgoingEdgeId":"znsrfgc25q483jdlqk84ix3l","content":{"logicalOperator":"OR","comparisons":[{"id":"cayzgkcwncbg71yd0w13jcfs","variableId":"vpppmv6tfnun3soi0kqd35677","comparisonOperator":"Equal to","value":"1"}]}},{"id":"k1dt05y72619xk4p3l778389","outgoingEdgeId":"qlo0s7ep416qge9fyogbkmsi","content":{"logicalOperator":"OR","comparisons":[{"id":"t0s9y2vcyhh18rxdq5p7eb77","variableId":"vpppmv6tfnun3soi0kqd35677","comparisonOperator":"Equal to","value":"2"}]}}]}]},{"id":"gh3w453qvgtd7orzsod0xy2v","title":"Atendimento ao Usuário - OPÇÃO 1","graphCoordinates":{"x":234.26,"y":-264.11},"blocks":[{"id":"a88gpk9w9of018dz9ejmsbx6","type":"Webhook","options":{"isCustomBody":true,"webhook":{"headers":[{"id":"by1yuiud7hh7bxkoc0j5zo26","key":"Content-Type","value":"application/json"}],"url":"https://SEU_DOMINIO_N8N.com/webhook/typebot-webhook","body":"{\n  \"telefone\": \"{{telefone}}\",\n  \"nome\": \"{{pushName}}\",\n  \"jid\": \"{{remoteJid}}\",\n  \"data\": \"{{data}}\",\n  \"hora\": \"{{hora}}\",\n  \"id\": \"{{id}}\",\n  \"instancia\": \"{{instanceName}}\",\n  \"opcao_digitada\": \"{{res}}\"\n}"}}},{"id":"kqctz5hkqmbb8el7s4ve4x01","type":"text","content":{"richText":[{"id":"X04YoHgVHq","type":"p","children":[{"text":"Segue abaixo a imagem do nosso Mini Porta-Paletes. "}]}]}},{"id":"zch7rnwqgtmn59tgzspwl7l2","type":"text","content":{"richText":[{"id":"XLA7imahic","type":"p","children":[{"text":"Obrigado pelas informações! 😊 Em breve, nossa equipe especializada irá te atender. "}]}]}}]},{"id":"n5clumlwvikcfrvj2rqhcw34","title":"Mensagem de resposta inválida","graphCoordinates":{"x":-228.38,"y":736.38},"blocks":[{"id":"kmteaa2ocfnda4l6w6x4uqc8","outgoingEdgeId":"jptmtehflmyw4bwiiirhs5y6","type":"text","content":{"richText":[{"id":"v5fJC6zm4G","type":"p","children":[{"text":"Você não digitou nenhuma opção correspondente. Tente novamente!"}]}]}}]},{"id":"uqin0pghyszc9gdal8vbhs3e","title":"Group #7","graphCoordinates":{"x":1698,"y":516},"blocks":[{"id":"yfa6fdhgky2bmalfkqis72s9","type":"text","content":{"richText":[{"id":"7BsVsnWbVd","type":"p","children":[{"bold":true,"text":"Para começar, escolha uma das opções abaixo:"}]},{"id":"j2cT7Ar1lk","type":"p","children":[{"text":""}]},{"id":"mjhWJjOVvj","type":"p","children":[{"text":"1️⃣ "},{"bold":true,"text":"Porta-Paletes"},{"text":"\n2️⃣ "},{"bold":true,"text":"Mini Porta-Paletes"}]},{"id":"SS_n02t4zX","type":"p","children":[{"text":""}]},{"id":"GoYajucD3f","type":"p","children":[{"text":"👉 "},{"text":"Digite apenas o número da opção desejada.","italic":true}]}]}}]},{"id":"pn32dlrg9ra8qeryv79wo5dv","title":"Declaração","graphCoordinates":{"x":-749.53,"y":-292.64},"blocks":[{"id":"v3gjchro2icuilh83926jrky","type":"Set variable","options":{"variableId":"virppa038ohy93oo1504tkn9b","expressionToEvaluate":"{{remoteJid}}","isCode":true}},{"id":"z0c9cvveoyo3oc1er671jg8a","type":"Set variable","options":{"variableId":"vtf885d3o0i7pzdl7e4iqq4qd","expressionToEvaluate":"{{pushName}}","isCode":true}},{"id":"i1nywsab7jhatshvjd4w4pup","type":"Set variable","options":{"variableId":"vbcwyhvp65giwtxrzr6vpqg8m","expressionToEvaluate":"{{remoteJid}}.split('@')[0]","isCode":true}},{"id":"umuetw2t8rj71elhzlgyqgzf","type":"Set variable","options":{"variableId":"vtx3nhgxvub6iernopferrnx6","expressionToEvaluate":"const agora = new Date();\n\nconst data = agora.toLocaleDateString('pt-BR', {\n  timeZone: 'America/Sao_Paulo'\n});\n\nreturn data;","isCode":true}},{"id":"h1n1lukvdz1vtugxxuctob5y","type":"Set variable","options":{"variableId":"vu5rtr3996p3we79za9kzgxrv","expressionToEvaluate":"const agora = new Date();\n\nconst hora = agora.toLocaleTimeString('pt-BR', {\n  timeZone: 'America/Sao_Paulo'\n});\n\nreturn hora;","isCode":true}},{"id":"egga1awo4wi9vj0v59ntc5vp","type":"Set variable","options":{"variableId":"vxrq3o466oduiq3r4ov14fn4n","expressionToEvaluate":"return Math.floor(Math.random() * 1000);","isCode":true}},{"id":"go58dqzn5ent5jk6drp3urqg","type":"Set variable","options":{"variableId":"vqi77m5wv4wnwnngsnkivymey","expressionToEvaluate":"{{instanceName}}","isCode":true}},{"id":"hi1xk0r9eakm5je3pwjjvg6x","outgoingEdgeId":"qx19z7ijaedjqem2c626w8x0","type":"Set variable","options":{"variableId":"vknm0jlu13nt0op8ygwq0csz4","expressionToEvaluate":"{{sessionId}}","isCode":true}}]},{"id":"th29gmhjhe6br26ljmuseph8","title":"Atendimento ao Usuário - OPÇÃO 2","graphCoordinates":{"x":237.38,"y":92.87},"blocks":[{"id":"ew84ny3y4l3mu3flz6k2qwqw","type":"Webhook","options":{"isCustomBody":true,"webhook":{"headers":[{"id":"by1yuiud7hh7bxkoc0j5zo26","key":"Content-Type","value":"application/json"}],"url":"https://SEU_DOMINIO_N8N.com/webhook/typebot-webhook","body":"{\n  \"telefone\": \"{{telefone}}\",\n  \"nome\": \"{{pushName}}\",\n  \"jid\": \"{{remoteJid}}\",\n  \"data\": \"{{data}}\",\n  \"hora\": \"{{hora}}\",\n  \"id\": \"{{id}}\",\n  \"instancia\": \"{{instanceName}}\",\n  \"opcao_digitada\": \"{{res}}\"\n}"}}},{"id":"k7t57qlt5lp0i5vxw0x5lgzv","type":"text","content":{"richText":[{"id":"X04YoHgVHq","type":"p","children":[{"text":"Segue abaixo a imagem do nosso Porta-Paletes. "}]}]}},{"id":"hbrq10dmepmsolpm5f4rmr65","type":"text","content":{"richText":[{"id":"XLA7imahic","type":"p","children":[{"text":"Obrigado pelas informações! 😊 Em breve, nossa equipe especializada irá te atender. "}]}]}}]}],"edges":[{"id":"znsrfgc25q483jdlqk84ix3l","from":{"blockId":"t5si14u2942hdocl91ikyzys","itemId":"zhr29u0ailqn8hzxqascn2tk"},"to":{"groupId":"gh3w453qvgtd7orzsod0xy2v"}},{"id":"jptmtehflmyw4bwiiirhs5y6","from":{"blockId":"kmteaa2ocfnda4l6w6x4uqc8"},"to":{"groupId":"xfz111nmk722d2gjtpdo7s04","blockId":"v0nhk4gdykkic8lstzakzlhh"}},{"id":"p5buc0wt4zud0dixxob6lfq7","from":{"blockId":"nzptq5i3mrpkkhylbi6tcr34"},"to":{"groupId":"xfz111nmk722d2gjtpdo7s04"}},{"id":"cxzi8bih4jb9secnam8gjryo","from":{"eventId":"fz652x59ej45iy6tzcur72vt"},"to":{"groupId":"pn32dlrg9ra8qeryv79wo5dv"}},{"id":"qb77z74qi32xqktw57p88wk8","from":{"blockId":"is7zbsmi8ggfuolv8y4md6ty"},"to":{"groupId":"xfz111nmk722d2gjtpdo7s04"}},{"id":"qlo0s7ep416qge9fyogbkmsi","from":{"blockId":"t5si14u2942hdocl91ikyzys","itemId":"k1dt05y72619xk4p3l778389"},"to":{"groupId":"th29gmhjhe6br26ljmuseph8"}},{"id":"qx19z7ijaedjqem2c626w8x0","from":{"blockId":"hi1xk0r9eakm5je3pwjjvg6x"},"to":{"groupId":"xfz111nmk722d2gjtpdo7s04"}}],"variables":[{"id":"vvnm32lxumiop4iyopwjt4j2y","name":"res_normalizado","isSessionVariable":true},{"id":"vhxnk7obhphz7x5bcqusb2t93","name":"/sair","isSessionVariable":true},{"id":"vknm0jlu13nt0op8ygwq0csz4","name":"sessionId","isSessionVariable":true},{"id":"vqi77m5wv4wnwnngsnkivymey","name":"instanceName","isSessionVariable":true},{"id":"vrvcuiy3lowzzjjcubsbojp0l","name":"instance","isSessionVariable":true},{"id":"vsxa5gmmri8s3zkpn6nsu3j38","name":"Instancia","isSessionVariable":true},{"id":"vimgwnzd7pput4vh92tdqegvh","name":"Intancia","isSessionVariable":true},{"id":"vxrq3o466oduiq3r4ov14fn4n","name":"id","isSessionVariable":true},{"id":"vu5rtr3996p3we79za9kzgxrv","name":"hora","isSessionVariable":true},{"id":"vtx3nhgxvub6iernopferrnx6","name":"data","isSessionVariable":true},{"id":"vuq4jqct4uvs64u4i71i8fjv3","name":"response","isSessionVariable":true},{"id":"vor0gs1ayn548dbivvm3ertj1","name":"{{response}}","isSessionVariable":true},{"id":"vg4pv8rn0nzt1vn6wke3i47my","name":"resposta","isSessionVariable":true},{"id":"vpqtrbeyj4uqkivrf33deg0wu","name":"respos","isSessionVariable":true},{"id":"vcj01iqs1voy52snmi8rzax8n","name":"lead","isSessionVariable":true},{"id":"vupoatos55ydyq49djvpxulpt","name":"todosdados","isSessionVariable":true},{"id":"vtf885d3o0i7pzdl7e4iqq4qd","name":"pushName","isSessionVariable":true},{"id":"vbcwyhvp65giwtxrzr6vpqg8m","name":"telefone","isSessionVariable":true},{"id":"virppa038ohy93oo1504tkn9b","name":"remoteJid","isSessionVariable":true},{"id":"vgw56ek2qebuzwl7guhgy3ruc","name":"nu","isSessionVariable":true},{"id":"vpppmv6tfnun3soi0kqd35677","name":"res","isSessionVariable":false},{"id":"vm4pc4l01jp125iikiqyrfxhz","name":"saudacao","isSessionVariable":true}],"theme":{"general":{"background":{"type":"Color","content":"#1D1D1D"}},"chat":{"hostBubbles":{"backgroundColor":"#0D0D0D","color":"#eeeeee","border":{"color":"#2a2a2a"}},"guestBubbles":{"backgroundColor":"#2a2a2a","color":"#eeeeee","border":{"color":"#3a3a3a"}},"buttons":{"backgroundColor":"#ff5924","color":"#eeeeee"},"inputs":{"backgroundColor":"#2a2a2a","color":"#eeeeee","border":{"color":"#484848"}}}},"selectedThemeTemplateId":"typebot-dark","settings":{"general":{"isBrandingEnabled":true,"systemMessages":{"invalidMessage":"Mensagem inválida. Por favor, tente novamente."}}},"createdAt":"2026-02-19T18:42:12.108Z","updatedAt":"2026-02-24T17:54:59.396Z","icon":null,"folderId":null,"publicId":"SEU_PUBLIC_ID","customDomain":null,"workspaceId":"SEU_WORKSPACE_ID","resultsTablePreferences":null,"isArchived":false,"isClosed":false,"whatsAppCredentialsId":null,"riskLevel":null}